README.md
setup.py
app/__init__.py
app/config.py
app/generic_runner.py
app/paths.py
etrm/__init__.py
etrm/dataset.py
etrm/dict_setup.py
etrm/dynamic_raster_finder.py
etrm/etrm_processes.py
etrm/preprocessing.py
etrm/raster.py
etrm/raster_manager.py
etrm/raster_tools.py
etrm/test_suite.py
etrm/time_series_manager.py
etrm/tools.py
etrm.egg-info/PKG-INFO
etrm.egg-info/SOURCES.txt
etrm.egg-info/dependency_links.txt
etrm.egg-info/requires.txt
etrm.egg-info/top_level.txt
runners/Cadol_multirun.py
runners/Esther_WGEW.py
runners/Soil_Moisture_EXU.py
runners/__init__.py
runners/ameriflux.py
runners/auto_pixel_grabber.py
runners/distributed_daily.py
runners/extract_inputs_pt_series.py
runners/interpolate_daily_ndvi.py
runners/interpolate_daily_ndvi_walnut.py
runners/rzs.py
runners/save_ndvi_bands.py
runners/soil_moisture_mapper.py
runners/taw_csv_gen2.py
runners/taw_mod_config_runner.py
runners/taw_mod_runner.py